datasette_geojson_map/__init__.py
datasette_geojson_map/static/leaflet-simplestyle.min.js
datasette_geojson_map/static/leaflet-simplestyle.min.js.map
datasette_geojson_map/static/map.css
datasette_geojson_map/static/map.js
datasette_geojson_map/static/map.js.map
datasette_geojson_map-0.5.0.dist-info/METADATA
datasette_geojson_map-0.5.0.dist-info/WHEEL
datasette_geojson_map-0.5.0.dist-info/entry_points.txt
datasette_geojson_map-0.5.0.dist-info/top_level.txt
datasette_geojson_map-0.5.0.dist-info/RECORD
