Metadata-Version: 2.1
Name: datasette-geojson-map
Version: 0.5.0
Summary: Render a map for any query with a geometry column
Home-page: https://github.com/eyeseast/datasette-geojson-map
Author: Chris Amico
License: Apache License, Version 2.0
Project-URL: Issues, https://github.com/eyeseast/datasette-geojson-map/issues
Project-URL: CI, https://github.com/eyeseast/datasette-geojson-map/actions
Project-URL: Changelog, https://github.com/eyeseast/datasette-geojson-map/releases
Requires-Python: >=3.6
Requires-Dist: datasette
Requires-Dist: datasette-geojson
Requires-Dist: datasette-leaflet
Provides-Extra: test
Requires-Dist: pytest; extra == "test"
Requires-Dist: pytest-asyncio; extra == "test"
Requires-Dist: geojson-to-sqlite; extra == "test"
